{
  "data": [
    {
      "id": "MDEwOlJlcG9zaXRvcnkzNDcwNzQ5NTM=",
      "name": "smile-detector-app",
      "createdAt": "2021-03-12T13:26:30Z",
      "url": "https://github.com/mahendragandham/smile-detector-app",
      "description": "Smile Detection App developed using python. It uses OpenCV library. This project will detect the smiling faces automatically in the webcam. When we run the project, it will open webcam and start detecting the faces.",
      "isFork": false,
      "languages": [
        {
          "name": "Python",
          "iconifyClass": "logos-python"
        },
        {
          "name": "OpenCV",
          "iconifyClass": "logos:opencv"
        }
      ]
    },
    {
      "id": "MDEwOlJlcG9zaXRvcnkzNDg3NjA2ODA=",
      "name": "Project Conqueror",
      "createdAt": "2021-03-17T15:32:13Z",
      "url": "https://github.com/mahendragandham/Conqueror",
      "description": "Conqueror is a Open Source Project. It is an Operating System developed using Linux Kernel. The Languages used in this project is Programming in C, x86_64 Assembly Language and Makefile. The development is in Low-level format.",
      "isFork": false,
      "languages": [
        {
          "name": "C",
          "iconifyClass": "logos:c"
        },
        {
          "name": "x86_64 Assembly",
          "iconifyClass": "vscode-icons:file-type-assembly"
        }
      ]
    },
    {
      "id": "MDEwOlJlcG9zaXRvcnkzNDQ4NDE5OTU=",
      "name": "Amazon Clone",
      "createdAt": "2021-03-05T14:50:54Z",
      "url": "https://github.com/mahendragandham/amazon-clone",
      "description": "This is a Clone website of amazon.com. This website is created using React JS. It displays the items list, you can add them to your cart and later you can delete them from the cart. It has a real time login data. The real cash payment is fetched from stripe.com. ",
      "isFork": false,
      "languages": [
        {
          "name": "JavaScript",
          "iconifyClass": "logos-javascript"
        },
        {
          "name": "HTML",
          "iconifyClass": "logos-html-5"
        },
        {
          "name": "CSS",
          "iconifyClass": "logos-css-3"
        }
      ]
    },
    {
      "id": "MDEwOlJlcG9zaXRvcnkzNDkwODU0MTc=",
      "name": "Voice-Assist-AI",
      "createdAt": "2021-03-18T13:32:08Z",
      "url": "https://github.com/mahendragandham/Voice-Assist-AI",
      "description": "Virtual Voice Assistant designed in Python. It will perform operations such as Web browsing, searching information in wikipedia, directly opens websites, calculates the age, etc..",
      "isFork": false,
      "languages": [
        {
          "name": "Python",
          "iconifyClass": "logos-python"
        }
      ]
    }
  ]
}
